<view name="org.eclipse.cdt.debug.ui.RegisterView">
    <table columns="16">
        <row>
            <cell>r0</cell>
            <cell>0.00000000</cell>
            <cell>r7</cell>
            <cell>0.36142747</cell>
            <cell>r14</cell>
            <cell>0.00007559</cell>
            <cell>r21</cell>
            <cell>0.00000000</cell>
            <cell>sp</cell>
            <cell>0.00007555</cell>
            <cell>21HR</cell>
            <cell>0.00000001</cell>
            <cell>LPE</cell>
            <cell>0.00004048</cell>
            <cell>sleep</cell>
            <cell>0.00000000</cell>
        </row>
        <row>
            <cell>r1</cell>
            <cell>0.00000000</cell>
            <cell>r8</cell>
            <cell>0.00000000</cell>
            <cell>r15</cell>
            <cell>0.00000000</cell>
            <cell>r22</cell>
            <cell>0.00000000</cell>
            <cell>ILNK1</cell>
            <cell>0.00000000</cell>
            <cell>stat</cell>
            <cell>-0.98436729</cell>
            <cell>ident</cell>
            <cell>-0.00000010</cell>
            <cell></cell>
            <cell></cell>
        </row>
        <row>
            <cell>r2</cell>
            <cell>0.00004395</cell>
            <cell>r9</cell>
            <cell>0.00000000</cell>
            <cell>r16</cell>
            <cell>0.00000000</cell>
            <cell>r23</cell>
            <cell>0.00000000</cell>
            <cell>ILNK2</cell>
            <cell>0.00000000</cell>
            <cell>stat32</cell>
            <cell>0.00000095</cell>
            <cell>debug</cell>
            <cell>0.25000000</cell>
            <cell></cell>
            <cell></cell>
        </row>
        <row>
            <cell>r3</cell>
            <cell>0.00004331</cell>
            <cell>r10</cell>
            <cell>0.00000000</cell>
            <cell>r17</cell>
            <cell>0.00007559</cell>
            <cell>r24</cell>
            <cell>0.00000000</cell>
            <cell>blink</cell>
            <cell>0.00003081</cell>
            <cell>statl1</cell>
            <cell>0.00000000</cell>
            <cell>pc</cell>
            <cell>0.00003082</cell>
            <cell></cell>
            <cell></cell>
        </row>
        <row>
            <cell>r4</cell>
            <cell>0.00000000</cell>
            <cell>r11</cell>
            <cell>0.00000000</cell>
            <cell>r18</cell>
            <cell>0.00004196</cell>
            <cell>r25</cell>
            <cell>0.00000000</cell>
            <cell>LPC</cell>
            <cell>0.00000000</cell>
            <cell>statl2</cell>
            <cell>0.00000000</cell>
            <cell>irqlv</cell>
            <cell>0.00000009</cell>
            <cell></cell>
            <cell></cell>
        </row>
        <row>
            <cell>r5</cell>
            <cell>0.00000000</cell>
            <cell>r12</cell>
            <cell>0.00000002</cell>
            <cell>r19</cell>
            <cell>0.00000000</cell>
            <cell>gp</cell>
            <cell>0.00004196</cell>
            <cell>pcl</cell>
            <cell>0.00003082</cell>
            <cell>sem</cell>
            <cell>0.00000000</cell>
            <cell>irq12</cell>
            <cell>0.00000000</cell>
            <cell></cell>
            <cell></cell>
        </row>
        <row>
            <cell>r6</cell>
            <cell>0.00007534</cell>
            <cell>r13</cell>
            <cell>0.00000000</cell>
            <cell>r20</cell>
            <cell>0.00000000</cell>
            <cell>fp</cell>
            <cell>0.00007555</cell>
            <cell>ZNCV</cell>
            <cell>0.00000191</cell>
            <cell>LPS</cell>
            <cell>0.00004048</cell>
            <cell>icnt</cell>
            <cell>0.00000228</cell>
            <cell></cell>
            <cell></cell>
        </row>
    </table>
</view>
